{
  "data": [
    {
      "Job_ID": "Job-001",
      "Experience": "2",
      "Image": "apple.svg",
      "Job_Title": "Senior IOS Developer",
      "Roll": "25 Applicants",
      "Category": "Software",
      "Location": "New York , USA",
      "Salary_Range": "30, 000 - 35, 000 / month",
      "Posted_Date": "12/09/2024"
    },
    {
      "Job_ID": "Job-002",
      "Experience": "4",
      "Image": "php.svg",
      "Job_Title": "Junior PHP Developer",
      "Roll": "20 Applicants",
      "Category": "Software",
      "Location": "Los Angeles, USA",
      "Salary_Range": "20, 000 - 25, 000 / month",
      "Posted_Date": "24/10/2024"
    }
  ],
  "totalData": 12
}